nitt_sw_login/__init__.py
nitt_sw_login/__main__.py
nitt_sw_login/utility_functions.py
nitt_sw_login-1.0.1.dist-info/DESCRIPTION.rst
nitt_sw_login-1.0.1.dist-info/METADATA
nitt_sw_login-1.0.1.dist-info/RECORD
nitt_sw_login-1.0.1.dist-info/WHEEL
nitt_sw_login-1.0.1.dist-info/entry_points.txt
nitt_sw_login-1.0.1.dist-info/metadata.json
nitt_sw_login-1.0.1.dist-info/top_level.txt
