Metadata-Version: 2.0
Name: nitt-sw-login
Version: 1.0.1
Summary: NITT Sonicwall Login Manager
Home-page: https://github.com/digaru19/NITT-SonicWall-Login
Author: Shubham Dighe
Author-email: digsblogger@gmail.com
License: BSD 3-clause "New" or "Revised" License
Keywords: nitt_sw_login nitt nit-trichy nitt-sw-login
Platform: UNKNOWN
Classifier: Environment :: Console
Classifier: Development Status :: 5 - Production/Stable
Classifier: Natural Language :: English
Classifier: Operating System :: OS Independent
Classifier: Programming Language :: Python
Classifier: Topic :: Internet :: WWW/HTTP :: Session
Requires-Dist: requests
Requires-Dist: PyOpenSSL
Requires-Dist: pyasn1
Requires-Dist: urllib3
Requires-Dist: ndg-httpsclient
